<?xml version="1.0" encoding="utf-8"?>
<clothing-items>
 <clothing>
  <id>
   241914348
  </id>
  <name>
   Brooks Shirt X-5494
  </name>
  <category>
   Shirt
  </category>
  <size>
   XXL
  </size>
  <color>
   Зеленый
  </color>
  <material>
   Шелк
  </material>
  <price>
   875236
  </price>
  <rating>
   4.58
  </rating>
  <reviews>
   833523
  </reviews>
  <sporty>
   no
  </sporty>
 </clothing>
 <clothing>
  <id>
   552708530
  </id>
  <name>
   Brooks Socks T-5111
  </name>
  <category>
   Socks
  </category>
  <size>
   M
  </size>
  <color>
   Оранжевый
  </color>
  <material>
   Шерсть
  </material>
  <price>
   489610
  </price>
  <rating>
   1.16
  </rating>
  <reviews>
   63063
  </reviews>
  <new>
   -
  </new>
 </clothing>
 <clothing>
  <id>
   993489260
  </id>
  <name>
   Addidas Belts Q-5125
  </name>
  <category>
   Belts
  </category>
  <size>
   M
  </size>
  <color>
   Оранжевый
  </color>
  <material>
   Вискоза
  </material>
  <price>
   321737
  </price>
  <rating>
   2.43
  </rating>
  <reviews>
   437905
  </reviews>
  <exclusive>
   yes
  </exclusive>
  <sporty>
   no
  </sporty>
 </clothing>
 <clothing>
  <id>
   364099924
  </id>
  <name>
   Fila Sweater M-8455
  </name>
  <category>
   Sweater
  </category>
  <size>
   XL
  </size>
  <color>
   Оранжевый
  </color>
  <material>
   Шерсть
  </material>
  <price>
   843402
  </price>
  <rating>
   3.02
  </rating>
  <reviews>
   392219
  </reviews>
  <new>
   -
  </new>
  <exclusive>
   no
  </exclusive>
  <sporty>
   no
  </sporty>
 </clothing>
 <clothing>
  <id>
   952273728
  </id>
  <name>
   Asics Socks D-6487
  </name>
  <category>
   Socks
  </category>
  <size>
   XXL
  </size>
  <color>
   Желтый
  </color>
  <material>
   Полиэстер
  </material>
  <price>
   297772
  </price>
  <rating>
   1.09
  </rating>
  <reviews>
   849877
  </reviews>
  <new>
   -
  </new>
  <exclusive>
   no
  </exclusive>
  <sporty>
   yes
  </sporty>
 </clothing>
 <clothing>
  <id>
   343296319
  </id>
  <name>
   Brooks Gloves K-3180
  </name>
  <category>
   Gloves
  </category>
  <size>
   XL
  </size>
  <color>
   Желтый
  </color>
  <material>
   Кожа
  </material>
  <price>
   561466
  </price>
  <rating>
   1.47
  </rating>
  <reviews>
   315371
  </reviews>
  <new>
   -
  </new>
  <sporty>
   no
  </sporty>
 </clothing>
 <clothing>
  <id>
   601408392
  </id>
  <name>
   Ellesse Shoes W-8580
  </name>
  <category>
   Shoes
  </category>
  <size>
   XL
  </size>
  <color>
   Синий
  </color>
  <material>
   Кожа
  </material>
  <price>
   199638
  </price>
  <rating>
   4.96
  </rating>
  <reviews>
   402524
  </reviews>
  <new>
   +
  </new>
  <exclusive>
   no
  </exclusive>
  <sporty>
   no
  </sporty>
 </clothing>
 <clothing>
  <id>
   661163536
  </id>
  <name>
   Reebok Blouse U-8153
  </name>
  <category>
   Blouse
  </category>
  <size>
   S
  </size>
  <color>
   Синий
  </color>
  <material>
   Лен
  </material>
  <price>
   591625
  </price>
  <rating>
   1.54
  </rating>
  <reviews>
   475096
  </reviews>
  <new>
   -
  </new>
  <exclusive>
   yes
  </exclusive>
 </clothing>
 <clothing>
  <id>
   434793335
  </id>
  <name>
   Addidas Belts V-2267
  </name>
  <category>
   Belts
  </category>
  <size>
   XL
  </size>
  <color>
   Красный
  </color>
  <material>
   Кожа
  </material>
  <price>
   236613
  </price>
  <rating>
   4.51
  </rating>
  <reviews>
   266638
  </reviews>
  <exclusive>
   yes
  </exclusive>
  <sporty>
   no
  </sporty>
 </clothing>
 <clothing>
  <id>
   772166051
  </id>
  <name>
   Brooks Jacket X-8181
  </name>
  <category>
   Jacket
  </category>
  <size>
   XXL
  </size>
  <color>
   Синий
  </color>
  <material>
   Шелк
  </material>
  <price>
   307652
  </price>
  <rating>
   4.59
  </rating>
  <reviews>
   119908
  </reviews>
  <exclusive>
   no
  </exclusive>
  <sporty>
   yes
  </sporty>
 </clothing>
 <clothing>
  <id>
   846010821
  </id>
  <name>
   Fila Blouse S-9861
  </name>
  <category>
   Blouse
  </category>
  <size>
   XL
  </size>
  <color>
   Голубой
  </color>
  <material>
   Лен
  </material>
  <price>
   866961
  </price>
  <rating>
   3.79
  </rating>
  <reviews>
   949603
  </reviews>
  <new>
   +
  </new>
  <sporty>
   no
  </sporty>
 </clothing>
 <clothing>
  <id>
   364854373
  </id>
  <name>
   Vans Gloves H-5142
  </name>
  <category>
   Gloves
  </category>
  <size>
   XL
  </size>
  <color>
   Фиолетовый
  </color>
  <material>
   Шерсть
  </material>
  <price>
   338703
  </price>
  <rating>
   4.49
  </rating>
  <reviews>
   633380
  </reviews>
  <new>
   +
  </new>
  <exclusive>
   yes
  </exclusive>
 </clothing>
 <clothing>
  <id>
   268192573
  </id>
  <name>
   Reebok Umbrellas J-3492
  </name>
  <category>
   Umbrellas
  </category>
  <size>
   XXL
  </size>
  <color>
   Оранжевый
  </color>
  <material>
   Хлопок
  </material>
  <price>
   265006
  </price>
  <rating>
   2.35
  </rating>
  <reviews>
   162648
  </reviews>
  <sporty>
   no
  </sporty>
 </clothing>
 <clothing>
  <id>
   846842463
  </id>
  <name>
   Reebok Umbrellas X-1455
  </name>
  <category>
   Umbrellas
  </category>
  <size>
   XL
  </size>
  <color>
   Зеленый
  </color>
  <material>
   Хлопок
  </material>
  <price>
   333105
  </price>
  <rating>
   1.04
  </rating>
  <reviews>
   874393
  </reviews>
  <new>
   -
  </new>
  <exclusive>
   yes
  </exclusive>
  <sporty>
   yes
  </sporty>
 </clothing>
 <clothing>
  <id>
   801136466
  </id>
  <name>
   Converse Shirt L-6398
  </name>
  <category>
   Shirt
  </category>
  <size>
   L
  </size>
  <color>
   Красный
  </color>
  <material>
   Полиэстер
  </material>
  <price>
   303207
  </price>
  <rating>
   3.02
  </rating>
  <reviews>
   980728
  </reviews>
  <new>
   -
  </new>
 </clothing>
 <clothing>
  <id>
   139397685
  </id>
  <name>
   Fila Shirt M-5820
  </name>
  <category>
   Shirt
  </category>
  <size>
   XL
  </size>
  <color>
   Красный
  </color>
  <material>
   Вискоза
  </material>
  <price>
   424974
  </price>
  <rating>
   3.66
  </rating>
  <reviews>
   863638
  </reviews>
  <new>
   +
  </new>
  <sporty>
   yes
  </sporty>
 </clothing>
</clothing-items>
