<?xml version="1.0" encoding="utf-8"?>
<clothing-items>
 <clothing>
  <id>
   276118932
  </id>
  <name>
   Addidas T-shirt C-5343
  </name>
  <category>
   T-shirt
  </category>
  <size>
   XXL
  </size>
  <color>
   Зеленый
  </color>
  <material>
   Шерсть
  </material>
  <price>
   527074
  </price>
  <rating>
   3.79
  </rating>
  <reviews>
   265473
  </reviews>
  <new>
   -
  </new>
  <exclusive>
   no
  </exclusive>
 </clothing>
 <clothing>
  <id>
   785281714
  </id>
  <name>
   Addidas Pants P-2369
  </name>
  <category>
   Pants
  </category>
  <size>
   XXL
  </size>
  <color>
   Голубой
  </color>
  <material>
   Хлопок
  </material>
  <price>
   661493
  </price>
  <rating>
   3.96
  </rating>
  <reviews>
   59432
  </reviews>
 </clothing>
 <clothing>
  <id>
   862880441
  </id>
  <name>
   DC Sweater J-2484
  </name>
  <category>
   Sweater
  </category>
  <size>
   M
  </size>
  <color>
   Красный
  </color>
  <material>
   Хлопок
  </material>
  <price>
   971139
  </price>
  <rating>
   1.13
  </rating>
  <reviews>
   574553
  </reviews>
 </clothing>
 <clothing>
  <id>
   511581740
  </id>
  <name>
   Brooks T-shirt T-7460
  </name>
  <category>
   T-shirt
  </category>
  <size>
   XXL
  </size>
  <color>
   Голубой
  </color>
  <material>
   Шелк
  </material>
  <price>
   852297
  </price>
  <rating>
   1.88
  </rating>
  <reviews>
   412409
  </reviews>
  <new>
   -
  </new>
  <exclusive>
   no
  </exclusive>
 </clothing>
 <clothing>
  <id>
   486039146
  </id>
  <name>
   New Balance Belts G-6395
  </name>
  <category>
   Belts
  </category>
  <size>
   L
  </size>
  <color>
   Красный
  </color>
  <material>
   Вискоза
  </material>
  <price>
   598656
  </price>
  <rating>
   4.69
  </rating>
  <reviews>
   516624
  </reviews>
  <new>
   +
  </new>
  <exclusive>
   no
  </exclusive>
  <sporty>
   no
  </sporty>
 </clothing>
 <clothing>
  <id>
   181218082
  </id>
  <name>
   DC Jacket G-8971
  </name>
  <category>
   Jacket
  </category>
  <size>
   M
  </size>
  <color>
   Синий
  </color>
  <material>
   Лен
  </material>
  <price>
   499049
  </price>
  <rating>
   1.39
  </rating>
  <reviews>
   298139
  </reviews>
  <new>
   -
  </new>
 </clothing>
 <clothing>
  <id>
   264740598
  </id>
  <name>
   Adidas Dress F-4138
  </name>
  <category>
   Dress
  </category>
  <size>
   S
  </size>
  <color>
   Голубой
  </color>
  <material>
   Вискоза
  </material>
  <price>
   702996
  </price>
  <rating>
   3.96
  </rating>
  <reviews>
   93740
  </reviews>
  <new>
   +
  </new>
  <exclusive>
   yes
  </exclusive>
 </clothing>
 <clothing>
  <id>
   177995840
  </id>
  <name>
   Addidas Shoes T-2716
  </name>
  <category>
   Shoes
  </category>
  <size>
   XXL
  </size>
  <color>
   Оранжевый
  </color>
  <material>
   Шерсть
  </material>
  <price>
   907627
  </price>
  <rating>
   2.05
  </rating>
  <reviews>
   473906
  </reviews>
  <exclusive>
   yes
  </exclusive>
  <sporty>
   no
  </sporty>
 </clothing>
 <clothing>
  <id>
   660725560
  </id>
  <name>
   Ellesse Shoes C-3563
  </name>
  <category>
   Shoes
  </category>
  <size>
   S
  </size>
  <color>
   Желтый
  </color>
  <material>
   Шелк
  </material>
  <price>
   425939
  </price>
  <rating>
   4.91
  </rating>
  <reviews>
   14071
  </reviews>
  <exclusive>
   yes
  </exclusive>
 </clothing>
 <clothing>
  <id>
   388660776
  </id>
  <name>
   Puma Handbags N-7079
  </name>
  <category>
   Handbags
  </category>
  <size>
   XXL
  </size>
  <color>
   Фиолетовый
  </color>
  <material>
   Вискоза
  </material>
  <price>
   958093
  </price>
  <rating>
   2.96
  </rating>
  <reviews>
   989273
  </reviews>
  <new>
   -
  </new>
  <exclusive>
   no
  </exclusive>
  <sporty>
   yes
  </sporty>
 </clothing>
 <clothing>
  <id>
   336445279
  </id>
  <name>
   Adidas Socks E-8264
  </name>
  <category>
   Socks
  </category>
  <size>
   S
  </size>
  <color>
   Голубой
  </color>
  <material>
   Шерсть
  </material>
  <price>
   184924
  </price>
  <rating>
   4.58
  </rating>
  <reviews>
   815952
  </reviews>
  <exclusive>
   no
  </exclusive>
  <sporty>
   yes
  </sporty>
 </clothing>
 <clothing>
  <id>
   479292834
  </id>
  <name>
   Nike Gloves G-9946
  </name>
  <category>
   Gloves
  </category>
  <size>
   XL
  </size>
  <color>
   Желтый
  </color>
  <material>
   Шелк
  </material>
  <price>
   786494
  </price>
  <rating>
   3.96
  </rating>
  <reviews>
   454198
  </reviews>
  <new>
   +
  </new>
 </clothing>
 <clothing>
  <id>
   703870801
  </id>
  <name>
   Under Armour Jacket V-4853
  </name>
  <category>
   Jacket
  </category>
  <size>
   M
  </size>
  <color>
   Синий
  </color>
  <material>
   Хлопок
  </material>
  <price>
   368015
  </price>
  <rating>
   4.89
  </rating>
  <reviews>
   302910
  </reviews>
  <new>
   -
  </new>
  <exclusive>
   no
  </exclusive>
  <sporty>
   yes
  </sporty>
 </clothing>
 <clothing>
  <id>
   178180030
  </id>
  <name>
   Reebok Umbrellas F-8814
  </name>
  <category>
   Umbrellas
  </category>
  <size>
   M
  </size>
  <color>
   Оранжевый
  </color>
  <material>
   Лен
  </material>
  <price>
   787787
  </price>
  <rating>
   3.38
  </rating>
  <reviews>
   320617
  </reviews>
  <exclusive>
   no
  </exclusive>
  <sporty>
   yes
  </sporty>
 </clothing>
 <clothing>
  <id>
   785725511
  </id>
  <name>
   Converse Pants O-9196
  </name>
  <category>
   Pants
  </category>
  <size>
   S
  </size>
  <color>
   Желтый
  </color>
  <material>
   Хлопок
  </material>
  <price>
   305614
  </price>
  <rating>
   1.51
  </rating>
  <reviews>
   482242
  </reviews>
  <exclusive>
   no
  </exclusive>
  <sporty>
   no
  </sporty>
 </clothing>
 <clothing>
  <id>
   114896638
  </id>
  <name>
   Lacoste Skirt A-7313
  </name>
  <category>
   Skirt
  </category>
  <size>
   XL
  </size>
  <color>
   Голубой
  </color>
  <material>
   Нейлон
  </material>
  <price>
   842891
  </price>
  <rating>
   2.72
  </rating>
  <reviews>
   183477
  </reviews>
  <new>
   +
  </new>
 </clothing>
 <clothing>
  <id>
   695792484
  </id>
  <name>
   Asics Shirt C-7961
  </name>
  <category>
   Shirt
  </category>
  <size>
   L
  </size>
  <color>
   Синий
  </color>
  <material>
   Хлопок
  </material>
  <price>
   641719
  </price>
  <rating>
   2.47
  </rating>
  <reviews>
   498870
  </reviews>
  <new>
   -
  </new>
  <sporty>
   yes
  </sporty>
 </clothing>
 <clothing>
  <id>
   366292529
  </id>
  <name>
   Puma T-shirt B-9219
  </name>
  <category>
   T-shirt
  </category>
  <size>
   M
  </size>
  <color>
   Оранжевый
  </color>
  <material>
   Нейлон
  </material>
  <price>
   645252
  </price>
  <rating>
   1.38
  </rating>
  <reviews>
   708414
  </reviews>
  <new>
   -
  </new>
  <sporty>
   no
  </sporty>
 </clothing>
 <clothing>
  <id>
   844773817
  </id>
  <name>
   Asics Blouse T-9433
  </name>
  <category>
   Blouse
  </category>
  <size>
   XL
  </size>
  <color>
   Оранжевый
  </color>
  <material>
   Хлопок
  </material>
  <price>
   737346
  </price>
  <rating>
   2.82
  </rating>
  <reviews>
   487597
  </reviews>
  <sporty>
   yes
  </sporty>
 </clothing>
 <clothing>
  <id>
   692957718
  </id>
  <name>
   Reebok Belts W-3599
  </name>
  <category>
   Belts
  </category>
  <size>
   XL
  </size>
  <color>
   Голубой
  </color>
  <material>
   Вискоза
  </material>
  <price>
   917687
  </price>
  <rating>
   2.02
  </rating>
  <reviews>
   704068
  </reviews>
  <new>
   -
  </new>
  <sporty>
   no
  </sporty>
 </clothing>
 <clothing>
  <id>
   711140903
  </id>
  <name>
   Asics Blouse M-2091
  </name>
  <category>
   Blouse
  </category>
  <size>
   L
  </size>
  <color>
   Красный
  </color>
  <material>
   Нейлон
  </material>
  <price>
   762922
  </price>
  <rating>
   3.74
  </rating>
  <reviews>
   367018
  </reviews>
  <new>
   +
  </new>
  <sporty>
   no
  </sporty>
 </clothing>
 <clothing>
  <id>
   411204534
  </id>
  <name>
   Lacoste Handbags H-9896
  </name>
  <category>
   Handbags
  </category>
  <size>
   M
  </size>
  <color>
   Зеленый
  </color>
  <material>
   Шерсть
  </material>
  <price>
   246385
  </price>
  <rating>
   2.82
  </rating>
  <reviews>
   721029
  </reviews>
  <new>
   -
  </new>
  <exclusive>
   no
  </exclusive>
 </clothing>
 <clothing>
  <id>
   945672650
  </id>
  <name>
   Under Armour Gloves L-6191
  </name>
  <category>
   Gloves
  </category>
  <size>
   XXL
  </size>
  <color>
   Оранжевый
  </color>
  <material>
   Шерсть
  </material>
  <price>
   971989
  </price>
  <rating>
   3.27
  </rating>
  <reviews>
   842114
  </reviews>
  <sporty>
   no
  </sporty>
 </clothing>
</clothing-items>
